pyboot/__init__.py
pyboot/cli/main.py
pyboot/cli/commands/__init__.py
pyboot/cli/commands/create.py
pyboot/cli/templates/project/db/etcdv3.db
pyboot/cli/templates/project/template/default/README.md.j2
pyboot/cli/templates/project/template/default/__init__.empty.py.j2
pyboot/cli/templates/project/template/default/__init__.py.j2
pyboot/cli/templates/project/template/default/app.py.j2
pyboot/cli/templates/project/template/default/app_config.py.j2
pyboot/cli/templates/project/template/default/component.boot.py.j2
pyboot/cli/templates/project/template/default/component.py.j2
pyboot/cli/templates/project/template/default/env.local.j2
pyboot/cli/templates/project/template/default/hello.controller.module.py.j2
pyboot/cli/templates/project/template/default/hello.controller.py.j2
pyboot/cli/templates/project/template/default/hello.dao.module.py.j2
pyboot/cli/templates/project/template/default/hello.dao.py.j2
pyboot/cli/templates/project/template/default/hello.service.module.py.j2
pyboot/cli/templates/project/template/default/hello.service.py.j2
pyboot/cli/templates/project/template/default/index.html.j2
pyboot/cli/templates/project/template/default/pyproject.component.toml.j2
pyboot/cli/templates/project/template/default/pyproject.toml.j2
pyboot/cli/templates/project/template/default/requirements.txt.j2
pyboot/cli/templates/project/template/default/utils.py.j2
pyboot/cli/templates/project/template/default/conf/application.yaml.j2
pyboot/cli/templates/project/template/default/conf/logback.yaml.j2
pyboot/cli/templates/project/template/default/conf/sql/sampleMapper.xml.j2
pyboot_cli-1.3.3.dist-info/licenses/LICENSE
pyboot_cli-1.3.3.dist-info/METADATA
pyboot_cli-1.3.3.dist-info/WHEEL
pyboot_cli-1.3.3.dist-info/entry_points.txt
pyboot_cli-1.3.3.dist-info/top_level.txt
pyboot_cli-1.3.3.dist-info/RECORD
